pyinstaller_setuptools/__init__.py
pyinstaller_setuptools/setup.py
pyinstaller_setuptools-2019.3.dist-info/COPYING
pyinstaller_setuptools-2019.3.dist-info/METADATA
pyinstaller_setuptools-2019.3.dist-info/WHEEL
pyinstaller_setuptools-2019.3.dist-info/top_level.txt
pyinstaller_setuptools-2019.3.dist-info/RECORD
